powerpoint_commenter/__init__.py
powerpoint_commenter/commenter.py
powerpoint_commenter/bin/DocumentFormat.OpenXml.Framework.dll
powerpoint_commenter/bin/DocumentFormat.OpenXml.dll
powerpoint_commenter/bin/PowerPointCommentAdder.deps.json
powerpoint_commenter/bin/PowerPointCommentAdder.dll
powerpoint_commenter/bin/PowerPointCommentAdder.exe
powerpoint_commenter/bin/PowerPointCommentAdder.pdb
powerpoint_commenter/bin/PowerPointCommentAdder.runtimeconfig.json
powerpoint_commenter/bin/System.IO.Packaging.dll
powerpoint_commenter-1.0.1.dist-info/METADATA
powerpoint_commenter-1.0.1.dist-info/WHEEL
powerpoint_commenter-1.0.1.dist-info/top_level.txt
powerpoint_commenter-1.0.1.dist-info/RECORD
