Metadata-Version: 2.4
Name: powerpoint-commenter
Version: 1.0.1
Summary: A Python package for adding comments to PowerPoint presentations using OpenXML SDK
Author-email: Munish Kumar <munishkumar19042002@gmail.com>
Project-URL: Homepage, https://github.com/munish0838/powerpoint-commenter
Project-URL: Bug Reports, https://github.com/munish0838/powerpoint-commenter/issues
Project-URL: Source, https://github.com/munish0838/powerpoint-commenter
Project-URL: Documentation, https://github.com/munish0838/powerpoint-commenter#readme
Keywords: powerpoint,comments,openxml,office,presentation,pptx,offline
Classifier: Development Status :: 4 - Beta
Classifier: Intended Audience :: Developers
Classifier: Operating System :: OS Independent
Classifier: Programming Language :: Python :: 3
Classifier: Programming Language :: Python :: 3.7
Classifier: Programming Language :: Python :: 3.8
Classifier: Programming Language :: Python :: 3.9
Classifier: Programming Language :: Python :: 3.10
Classifier: Programming Language :: Python :: 3.11
Classifier: Programming Language :: Python :: 3.12
Classifier: Topic :: Office/Business :: Office Suites
Classifier: Topic :: Software Development :: Libraries :: Python Modules
Classifier: Topic :: Text Processing :: Markup
Requires-Python: >=3.7
